Dockerfile
LICENSE
MANIFEST.in
README.rst
requirements.txt
setup.cfg
setup.py
roip/__init__.py
roip/classes.py
roip/constants.py
roip.egg-info/PKG-INFO
roip.egg-info/SOURCES.txt
roip.egg-info/dependency_links.txt
roip.egg-info/not-zip-safe
roip.egg-info/requires.txt
roip.egg-info/top_level.txt