Metadata-Version: 1.1
Name: roip
Version: 1.0.0
Summary: Python Radio Over IP Module.
Home-page: https://github.com/ampledata/roip
Author: Greg Albrecht
Author-email: oss@undef.net
License: Copyright 2018 Orion Labs, Inc.
